forge/__init__.py
forge/cli.py
forge/exceptions.py
forge/forge.py
forge/pipx_wrapper.py
tele_forge-2.0.1.dist-info/LICENSE
tele_forge-2.0.1.dist-info/METADATA
tele_forge-2.0.1.dist-info/WHEEL
tele_forge-2.0.1.dist-info/entry_points.txt
tele_forge-2.0.1.dist-info/top_level.txt
tele_forge-2.0.1.dist-info/zip-safe
tele_forge-2.0.1.dist-info/RECORD
