Metadata-Version: 2.1
Name: tele-forge
Version: 2.0.1
Summary: convenient cli with extendable collection of useful plugins
Home-page: https://github.com/TeleTrackingTechnologies/forge
Author: Brandon Horn, Kenneth Poling, Paul Verardi, Cameron Tucker, Clint Wadley, Morgan Szafranski
Author-email: opensource@teletracking.com
License: MIT
Platform: UNKNOWN
Classifier: Programming Language :: Python :: 3
Classifier: Programming Language :: Python :: 3.7
Classifier: Programming Language :: Python :: 3.8
Classifier: Programming Language :: Python :: 3.9
Classifier: License :: OSI Approved :: MIT License
Classifier: Operating System :: OS Independent
Requires-Python: >=3.7
Requires-Dist: requests (==2.25.0)
Requires-Dist: tabulate (==0.8.7)
Requires-Dist: halo (==0.0.31)
Requires-Dist: python-slugify (==4.0.1)
Requires-Dist: click (==7.1.2)
